{
    "北京市": {
        "北京": "Wqsps",
        "昌平": "niStC",
        "朝阳": "MjXfi",
        "大兴": "iEilj",
        "房山": "sNifH",
        "丰台": "WgwUa",
        "海淀": "fElIR",
        "怀柔": "zWIHa",
        "门头沟": "MNFUM",
        "密云": "SlmGF",
        "平谷": "WKTDr",
        "石景山": "TKDWT",
        "顺义": "MKoqG",
        "通州": "UXDVf",
        "延庆": "FzrMk"
    },
    "天津市": {
        "黑牛城": "eAfAu",
        "宝坻": "gxHKu",
        "北辰": "FeuUa",
        "东丽": "GiGuJ",
        "蓟州": "eiGrT",
        "津南": "luSKF",
        "静海": "RvNCI",
        "宁河": "mfQUa",
        "塘沽": "KKlDi",
        "武清": "AAHhS",
        "西青": "rerpc"
    },
    "河北省": {
        "石家庄": "uJQqI",
        "保定": "FaykR",
        "沧州": "mHkdW",
        "承德": "oWYwK",
        "邯郸": "AwDQd",
        "衡水": "Jiheq",
        "廊坊": "gXmTp",
        "鹿泉": "rlWKm",
        "秦皇岛": "SBrmr",
        "任丘": "nBdMW",
        "容城": "iqimR",
        "唐山": "aCRJR",
        "邢台": "WgyJx",
        "张家口": "AXmqR",
        "安国": "vceHS",
        "安平": "yeGPa",
        "安新": "UujiJ",
        "霸州": "kgrJx",
        "柏乡": "dVXww",
        "渤海新区黄骅": "hIkaB",
        "泊头": "pSXjM",
        "曹妃甸": "wrjjn",
        "曹妃甸零公里": "qXsSz",
        "昌黎": "vTGXA",
        "成安": "HMSVy",
        "承德县": "WYnNt",
        "赤城": "yeGWo",
        "崇礼": "pOnxu",
        "磁县": "vQqbv",
        "大厂": "VzbqG",
        "大城": "qitbz",
        "大名": "ylLRu",
        "定州": "EXTBR",
        "东光": "BRTol",
        "肥乡": "JnWfX",
        "丰南": "dLkgL",
        "丰宁": "MnxTS",
        "丰润": "Aaghn",
        "峰峰": "eRyds",
        "抚宁": "TAGXi",
        "阜城": "lOwCw",
        "阜平": "XELos",
        "高碑店": "nSuxQ",
        "高阳": "QIPjL",
        "高邑": "Slmxc",
        "沽源": "bsXrE",
        "故城": "eRflS",
        "固安": "RSzaV",
        "馆陶": "cAOkd",
        "广平": "fQMyR",
        "广宗": "mKRmY",
        "海兴": "kqMHD",
        "河间": "pWduF",
        "怀安": "GKAfR",
        "怀来": "TNNEz",
        "鸡泽": "AGkyS",
        "冀州": "qllqX",
        "晋州": "vGudX",
        "井陉": "PxsDy",
        "景县": "gMmSA",
        "巨鹿": "XXUYp",
        "康保": "KcroZ",
        "宽城": "aQZks",
        "乐亭": "BygfA",
        "临城": "tBOjo",
        "临西": "quDcn",
        "临漳": "iStnu",
        "灵寿": "TynGR",
        "隆化": "KkHVu",
        "隆尧": "CoRNr",
        "卢龙": "uszcX",
        "滦南": "RlsNU",
        "滦平": "gPeaq",
        "滦州": "zbjeL",
        "满城": "zHLty",
        "孟村": "gKfij",
        "南宫": "QDdHX",
        "南和": "HjWcO",
        "南皮": "EtUJU",
        "内丘": "tbLfc",
        "宁晋": "QwGch",
        "平泉": "rhIky",
        "平山": "lzuFh",
        "平乡": "cOXrB",
        "迁安": "qUXcf",
        "迁西": "qvzeN",
        "青龙": "DlwUH",
        "青县": "tspDy",
        "清河": "zUBhk",
        "邱县": "uEdAG",
        "曲阳": "KVJiP",
        "曲周": "fAOhd",
        "饶阳": "VyOJb",
        "任泽": "zkSoL",
        "三河": "qSdEK",
        "沙河": "DPtSW",
        "尚义": "BukSn",
        "涉县": "YueHa",
        "深泽": "vGtXb",
        "深州": "upNrO",
        "顺平": "AFgnu",
        "肃宁": "gZrxg",
        "唐县": "IIPwa",
        "万全": "nXeQi",
        "望都": "uvaeY",
        "威县": "LzLae",
        "围场": "hbBle",
        "蔚县": "YbKUt",
        "魏县": "JdkhE",
        "文安": "TKCta",
        "无极": "YGoOp",
        "吴桥": "MHgRX",
        "武安": "FwHWv",
        "武强": "KZDpU",
        "武邑": "NiqiA",
        "献县": "KCdLb",
        "香河": "xWfUk",
        "辛集": "HdwIC",
        "新河": "YGLDG",
        "新乐": "xNnEo",
        "兴隆": "qWokG",
        "行唐": "rZAWC",
        "雄县": "FTACx",
        "徐水": "VNsra",
        "宣化": "bLxvu",
        "盐山": "lqiAy",
        "阳原": "daicd",
        "易县": "mnilQ",
        "永年": "bJQcD",
        "永清": "DaCoA",
        "玉田": "SHtYc",
        "元氏": "XHFGV",
        "赞皇": "mEbhg",
        "枣强": "PZHKx",
        "张北": "Ykfmn",
        "赵县": "yXSFQ",
        "正定": "sENtA",
        "遵化": "Bcxig",
        "藁城": "BMDXb",
        "涞源": "ZdmWW",
        "涿鹿": "oqgGH",
        "涿州": "BGCup",
        "栾城": "vPoEm",
        "蠡县": "yYUQU"
    },
    "山西省": {
        "太原": "jmHMK",
        "大同": "VZgct",
        "晋城": "VKljS",
        "黎城": "rDABI",
        "离石": "lOfKI",
        "临汾": "nhsiM",
        "平遥": "ShbMD",
        "上党": "FkfwN",
        "朔州": "OtlfP",
        "文水": "NFJlP",
        "五台山": "sxucp",
        "忻府": "lkWYa",
        "阳泉": "rwUnO",
        "运城": "AupnI",
        "安泽": "KSSLi",
        "保德": "JXVvw",
        "长子": "Siujx",
        "大宁": "ekOlr",
        "代县": "atrjZ",
        "定襄": "NkWQP",
        "繁峙": "OTNAe",
        "方山": "zAYzL",
        "汾西": "ZqAPc",
        "汾阳": "SsPhi",
        "浮山": "MYXsS",
        "高平": "RJOci",
        "古交": "ZCnNp",
        "古县": "FCrZy",
        "广灵": "pbxDH",
        "和顺": "tOgRV",
        "河津": "oblOm",
        "河曲": "HvYyw",
        "洪洞": "mwSUY",
        "侯马": "ZGhqJ",
        "壶关": "kCXTL",
        "怀仁": "Ggdzs",
        "浑源": "uWhuB",
        "霍州": "DiJSX",
        "吉县": "AFVkU",
        "尖草坪": "ANMfd",
        "交城": "HHUAJ",
        "交口": "RAxFj",
        "介休": "KqHyx",
        "静乐": "KcsUl",
        "临县": "bAyTQ",
        "临猗": "hGfmL",
        "灵丘": "cyeJN",
        "灵石": "sGCZR",
        "陵川": "EeGzR",
        "柳林": "aKlRm",
        "娄烦": "TxZCB",
        "潞城": "yGPnj",
        "宁武": "CRNDj",
        "偏关": "ygqJc",
        "平定": "DFvwn",
        "平鲁": "oJway",
        "平陆": "PFPpH",
        "平顺": "jWYMB",
        "蒲县": "mxfxi",
        "祁县": "gBnmM",
        "沁水": "hvopq",
        "沁县": "MizAK",
        "沁源": "UEqUT",
        "清徐": "tIwCB",
        "曲沃": "OYMED",
        "山阴": "KXQMd",
        "神池": "tBsIw",
        "石楼": "CEGWS",
        "寿阳": "FlXtf",
        "太谷": "kfLqv",
        "天镇": "qtSfk",
        "屯留": "IUDAF",
        "万荣": "lSPZr",
        "闻喜": "lWKfw",
        "武乡": "zJdqY",
        "五台": "AMKDZ",
        "五寨": "vMDNU",
        "昔阳": "ThJbh",
        "夏县": "LetlZ",
        "襄汾": "ZlvFx",
        "襄垣": "WDsDq",
        "乡宁": "fwMED",
        "小店": "hGDQB",
        "孝义": "VtRVI",
        "新绛": "wHrOw",
        "兴县": "RBGVZ",
        "阳城": "twIgf",
        "阳高": "jLWui",
        "阳曲": "JOoEL",
        "翼城": "VXrqE",
        "应县": "LVEDc",
        "永和": "Xmsxf",
        "永济": "QGpNZ",
        "右玉": "cXBlU",
        "盂县": "YZvdq",
        "榆次": "CKjmA",
        "榆社": "mQwJl",
        "垣曲": "HbPQe",
        "原平": "ENVfK",
        "云州": "eLCyB",
        "中阳": "QOTQG",
        "左权": "VFmuE",
        "左云": "bkbPS",
        "隰县": "WVCsi",
        "芮城": "reeTF",
        "岚县": "Prpqh",
        "岢岚": "ucItd",
        "绛县": "JpoNT",
        "稷山": "FJUIg"
    },
    "内蒙古自治区": {
        "呼和浩特": "IlyWx",
        "阿拉善右旗": "SfktK",
        "阿拉善左旗": "ijwRt",
        "巴林右旗": "tUiFh",
        "包头": "wzspS",
        "赤峰": "yiSxk",
        "东胜": "RPPfG",
        "二连浩特": "OJrdF",
        "海拉尔": "ZnVfr",
        "集宁": "pZpJB",
        "临河": "lqHEq",
        "通辽": "LUAqU",
        "乌海": "HfJln",
        "乌兰浩特": "UbrmG",
        "锡林浩特": "ipFRY",
        "阿巴嘎旗": "JokSy",
        "阿尔山": "dfCWY",
        "阿鲁科尔沁旗": "FQZtL",
        "阿荣旗": "cYTae",
        "敖汉旗": "luTCQ",
        "八里罕": "ATOFT",
        "巴林左旗": "ekOdZ",
        "巴雅尔吐胡硕": "qTuUm",
        "巴彦诺日公": "wutxB",
        "白云鄂博": "tPIAd",
        "宝国吐": "QUgIO",
        "博克图": "qRnkd",
        "察哈尔右翼前旗": "KLonh",
        "察右后旗": "kCGgC",
        "察右中旗": "bmgqt",
        "陈巴尔虎旗": "RLQwC",
        "达尔罕茂明安联合旗": "kcVBl",
        "达拉特旗": "GQBuT",
        "大佘太": "yIiHA",
        "东乌珠穆沁旗": "oxWik",
        "多伦": "AinEl",
        "额尔古纳": "KXNSC",
        "额济纳旗": "Tskoj",
        "鄂伦春自治旗": "xSEoe",
        "鄂托克旗": "EoybG",
        "鄂托克前旗": "fyQnv",
        "鄂温克族自治旗": "fsMrH",
        "丰镇": "uGHht",
        "富河": "icsSH",
        "岗子": "pGWDF",
        "高力板": "KgMGe",
        "根河": "VRnKw",
        "固阳": "WyJDB",
        "拐子湖": "voiPf",
        "海力素": "JwQIK",
        "杭锦后旗": "nxQJT",
        "杭锦旗": "SycQs",
        "和林格尔县": "zubiG",
        "河南": "jNnwV",
        "胡尔勒": "yvgzq",
        "化德": "wsLwr",
        "霍林郭勒": "NyoHN",
        "吉兰泰": "IQilY",
        "喀喇沁旗": "FDRnn",
        "开鲁": "EXBSC",
        "康巴什体育中心": "kHoWx",
        "科尔沁右翼中旗": "ruoKn",
        "科左后旗": "dYsXY",
        "科左中旗": "ZBZEe",
        "克什克腾旗": "bZqhw",
        "库伦旗": "ldsso",
        "凉城": "uZabW",
        "林西": "pVsnu",
        "孪井滩": "LRYsR",
        "满都拉": "VOxXA",
        "满洲里": "lpQez",
        "莫力达瓦达斡尔族自治旗": "EDzaW",
        "那仁宝力格": "prTEI",
        "奈曼旗": "iBrpm",
        "宁城": "PgPDX",
        "青龙山": "dKioY",
        "清水河": "kdzjw",
        "赛罕": "cTjEd",
        "商都": "gBnSb",
        "舍伯吐": "EMAsi",
        "四子王旗": "rWZNd",
        "苏尼特右旗": "TkuWv",
        "苏尼特左旗": "vHEXp",
        "索伦": "rAVUr",
        "太仆寺旗": "ckJon",
        "突泉": "jreCm",
        "图里河": "aJvlD",
        "土默特右旗": "vzhvA",
        "土默特左旗": "XSgaX",
        "托克托": "PKpIA",
        "翁牛特旗": "GVRzp",
        "乌拉盖": "WFTLX",
        "乌拉特后旗": "EbPeZ",
        "乌拉特前旗": "qxqVQ",
        "乌拉特中旗": "BdifC",
        "乌审旗": "KhrDm",
        "乌审召": "jNLyR",
        "乌斯太": "AmXjG",
        "武川": "LDamn",
        "五原": "mWFOR",
        "西乌珠穆沁旗": "celHs",
        "希拉穆仁": "cixAo",
        "镶黄旗": "OWEcY",
        "小二沟": "hYgyL",
        "新巴尔虎右旗": "GVqqU",
        "新巴尔虎左旗": "HEXvi",
        "兴和": "BtVpC",
        "牙克石": "Djmsc",
        "雅布赖": "PHwZB",
        "伊金霍洛旗": "bavSd",
        "伊克乌素": "QDdlB",
        "扎兰屯": "SkEfQ",
        "扎鲁特旗": "KhOia",
        "扎赉特旗": "XPlcN",
        "正蓝旗": "cxbVU",
        "正镶白旗": "LxGsx",
        "朱日和": "HdUca",
        "准格尔旗": "mrfbj",
        "卓资": "BQQKj",
        "磴口": "CaZRE"
    },
    "辽宁省": {
        "沈阳": "xasvS",
        "鞍山": "TopGN",
        "本溪": "fZXDt",
        "朝阳": "SSCPq",
        "大连": "nGPyb",
        "丹东": "DlvsN",
        "阜新": "uxzEA",
        "锦州": "LgDdn",
        "连山区": "Qiolo",
        "辽阳": "kgqfX",
        "盘山": "cXRsH",
        "铁岭": "WDQHL",
        "瓦房店": "IxHPA",
        "新宾": "CDFHM",
        "营口": "veIOe",
        "北票": "UkMeR",
        "北镇": "OMHFX",
        "本溪县": "NJVFd",
        "昌图": "BZlSQ",
        "长海": "KKlGS",
        "大石桥": "oCPAd",
        "大洼": "bHIoG",
        "灯塔": "rtLUT",
        "东港": "TDsJF",
        "法库": "qNemb",
        "凤城": "ORxzx",
        "抚顺": "shhKE",
        "盖州": "iTeZl",
        "海城": "FEiUD",
        "黑山": "sNHAg",
        "桓仁": "YFYje",
        "建昌": "gkBIR",
        "建平": "SNUdT",
        "金州": "ztLuW",
        "喀左": "syxYZ",
        "开原": "TlVpC",
        "康平": "BNXKe",
        "宽甸": "NevSD",
        "辽阳县": "UGdju",
        "辽中": "cssdK",
        "凌海": "vdydi",
        "凌源": "fSStg",
        "旅顺": "CfIAL",
        "普兰店": "PPJcn",
        "清原": "TAkZv",
        "绥中": "YFjmk",
        "台安": "pLCPo",
        "西丰": "arJtC",
        "新民": "eIJxg",
        "兴城": "YItXH",
        "熊岳": "ntTRe",
        "义县": "VXqUh",
        "章党": "TgxoR",
        "彰武": "NfXsS",
        "庄河": "RByQD",
        "岫岩": "FzPMK"
    },
    "吉林省": {
        "长春": "mxFBj",
        "白城": "ktvDN",
        "白山": "nFNOH",
        "吉林城郊": "bQxQX",
        "集安": "qTfcE",
        "辽源": "pSYcD",
        "梅河口": "aEizR",
        "四平": "UIlgs",
        "松原": "jJpzl",
        "通化": "LaBrf",
        "延吉": "SgNIn",
        "珲春": "svLkX",
        "桦甸": "Eanln",
        "安图": "sKOvI",
        "长白": "rZsMv",
        "长岭": "oLJTA",
        "大安": "yHPvq",
        "德惠": "biKXr",
        "东丰": "yGbVo",
        "东岗": "VVKCO",
        "敦化": "ZgUQB",
        "二道": "jeQFa",
        "扶余": "PHfqQ",
        "抚松": "HRRIh",
        "公主岭": "OHlxo",
        "和龙": "VEYqP",
        "辉南": "pzlTe",
        "靖宇": "MZJvo",
        "九台": "NSawy",
        "梨树": "rtLqz",
        "临江": "YSNnc",
        "柳河": "nBBbT",
        "龙井": "YIufU",
        "农安": "wTAnf",
        "磐石": "vIHTg",
        "乾安": "xUMET",
        "前郭": "JWcDH",
        "舒兰": "vGcsn",
        "双辽": "ZAyGR",
        "双阳": "DPsgS",
        "通化县": "bVSUm",
        "通榆": "cdzFO",
        "图们": "hulhW",
        "汪清": "DuMLb",
        "伊通": "HHeks",
        "永吉": "ysQUB",
        "榆树": "pOntg",
        "镇赉": "fboAj",
        "洮南": "YWjdQ",
        "蛟河": "BneiY"
    },
    "黑龙江省": {
        "哈尔滨": "pzXOG",
        "爱辉": "pmtBg",
        "北林": "gSmNE",
        "勃利": "HeDuS",
        "大庆": "uLCaf",
        "杜尔伯特": "exRbg",
        "甘南": "sjFeU",
        "鹤岗": "pQrYF",
        "鸡西": "tsmWc",
        "佳木斯": "IwveF",
        "加格达奇": "bzkiu",
        "漠河": "JRtnt",
        "牡丹江": "WhkSY",
        "七台河": "olTln",
        "齐齐哈尔": "pMfJu",
        "双鸭山": "xYzrU",
        "绥芬河": "PtgOS",
        "伊春": "BAQLD",
        "阿城": "xQbWX",
        "安达": "NNObw",
        "巴彦": "pWcDo",
        "拜泉": "lNOID",
        "宝清": "YjqxY",
        "北安": "FUBSc",
        "宾县": "yiPrH",
        "东宁": "tALrP",
        "方正": "pIYbE",
        "抚远": "DVtZN",
        "富锦": "klLFj",
        "富裕": "dpauo",
        "海林": "mbyFX",
        "海伦": "NTbXS",
        "呼兰": "wqBvY",
        "呼玛": "mgshy",
        "呼中": "UYVbv",
        "虎林": "rhGIi",
        "鸡东": "NFjTg",
        "集贤": "KwYPC",
        "嘉荫": "YNpgg",
        "克东": "itNzm",
        "克山": "CbmDS",
        "兰西": "cGaLJ",
        "林甸": "gleUW",
        "林口": "CfgiH",
        "龙江": "nIDJi",
        "萝北": "PWpUL",
        "密山": "yqikp",
        "明水": "KiOjO",
        "木兰": "SZwbc",
        "穆棱": "ztosr",
        "嫩江": "vbooM",
        "宁安": "ieErV",
        "青冈": "vIgUg",
        "庆安": "yTeZo",
        "饶河": "wFzHQ",
        "尚志": "JAcDZ",
        "双城": "eXUdr",
        "绥滨": "SJgvR",
        "绥棱": "yDfoU",
        "孙吴": "mmcxS",
        "塔河": "CDeOK",
        "泰来": "xcfkz",
        "汤旺": "ZGvkf",
        "汤原": "vroJw",
        "铁力": "ADOZr",
        "通河": "psRwx",
        "同江": "qrZkO",
        "望奎": "sLrQJ",
        "五常": "wDTbt",
        "五大连池": "hkmNX",
        "五营": "hhuDQ",
        "新林": "HbMIl",
        "逊克": "mWSYM",
        "延寿": "pvnEo",
        "依安": "bsEJz",
        "依兰": "dmjQR",
        "友谊": "uxvdb",
        "肇东": "Ksney",
        "肇源": "aurwd",
        "肇州": "Yopij",
        "讷河": "ASmKv",
        "桦川": "DOodT",
        "桦南": "jLgCL"
    },
    "上海市": {
        "徐家汇": "bwUMl",
        "宝山": "QtPRO",
        "崇明": "fndTJ",
        "奉贤": "BOoen",
        "嘉定": "HZYrL",
        "金山": "XJLoP",
        "浦东": "atcMf",
        "青浦": "xZqWL",
        "松江": "FkyWg",
        "闵行": "ttcsH"
    },
    "江苏省": {
        "南京": "CxOWZ",
        "常州": "bmyrb",
        "东台": "OYMXg",
        "赣榆": "tPkeh",
        "高邮": "DRlfC",
        "淮安区": "DXKse",
        "连云港": "HPnPL",
        "南通": "VHAmf",
        "苏州": "lqYjK",
        "宿迁": "jVxXh",
        "泰州": "kQswL",
        "无锡": "fvlMy",
        "徐州": "bWGZQ",
        "盐都": "XABKt",
        "扬州": "lDhJo",
        "镇江": "xKfDh",
        "盱眙": "HQORe",
        "宝应": "ojvBC",
        "滨海": "Yjdlm",
        "常熟": "ZZNyr",
        "大丰": "ZAxsG",
        "丹阳": "tCUFF",
        "东海": "fiwPx",
        "丰县": "WUcbj",
        "阜宁": "AnpOV",
        "高淳": "nihEu",
        "灌南": "ChsOC",
        "灌云": "SQNaH",
        "海安": "EImCv",
        "海门": "OJsnx",
        "洪泽": "sZMPB",
        "淮阴": "QNRHc",
        "建湖": "KjVdj",
        "姜堰": "GNnVR",
        "江都": "KZXUZ",
        "江宁": "Dfezs",
        "江阴": "aBsDt",
        "金湖": "LhZvh",
        "金坛区": "aZxdI",
        "靖江": "qgNae",
        "句容": "HzWJm",
        "昆山": "OxFhx",
        "涟水": "ktyzF",
        "六合": "veJzt",
        "沛县": "HQOOW",
        "浦口": "ssDyH",
        "启东": "omKcH",
        "如东": "EseOS",
        "如皋": "UWfDb",
        "射阳": "ezmfH",
        "泰兴": "pzmbN",
        "太仓": "ZOrBB",
        "通州": "EvnXS",
        "吴江": "Oimbc",
        "响水": "ZQVMR",
        "新沂": "hDLrj",
        "兴化": "fzEWw",
        "扬中": "KwLGW",
        "仪征": "KcQmD",
        "宜兴": "AGnXn",
        "张家港": "ZGGdV",
        "邳州": "EizdM",
        "沭阳": "UBFXu",
        "泗洪": "wKIff",
        "泗阳": "wtsbS",
        "溧水": "gRnAT",
        "溧阳": "SOYVx",
        "睢宁": "tdTgS"
    },
    "浙江省": {
        "杭州": "HIieJ",
        "定海": "MbBco",
        "洞头": "VNwVr",
        "嘉兴": "pxfeS",
        "金华": "QMNma",
        "景宁": "uqdix",
        "柯桥": "VzTiT",
        "丽水": "nEoHv",
        "莲都": "DYqLs",
        "临安": "rPweL",
        "临海": "hQdlP",
        "临平": "uymCz",
        "宁波": "XjZpe",
        "宁海": "leUlH",
        "磐安": "QxmlB",
        "平湖": "TJTpA",
        "绍兴": "gxbHp",
        "松阳": "kGfEH",
        "温州": "qgMmM",
        "镇海": "VdwKZ",
        "舟山": "KElec",
        "鄞州": "TNaZf",
        "嵊州": "nySsV",
        "衢州": "ydEbu",
        "安吉": "qytam",
        "北仑": "fTHFh",
        "苍南": "GvzGe",
        "常山": "PbRMS",
        "长兴": "nhdEv",
        "淳安": "DUufR",
        "慈溪": "LlhKr",
        "德清": "FVPPn",
        "东阳": "IdQKQ",
        "奉化": "fBeVR",
        "富阳": "fCxxp",
        "海宁": "KqlbA",
        "海曙": "icFyg",
        "海盐": "Guoip",
        "湖州": "quMLV",
        "黄岩": "ScBYE",
        "嘉善": "UvOFB",
        "建德": "UVshw",
        "江北": "sFzyX",
        "江山": "GJsUv",
        "椒江": "hqPdG",
        "开化": "JZNGR",
        "兰溪": "qgpLh",
        "乐清": "XIkhp",
        "龙港": "ibexn",
        "龙泉": "IFYzG",
        "龙游": "JrShZ",
        "路桥": "HDqqP",
        "南浔": "mWMSb",
        "平阳": "mAnvB",
        "普陀": "Dcmkn",
        "浦江": "jNOUm",
        "钱塘": "wtWUe",
        "青田": "BErcS",
        "庆元": "eAFNK",
        "瑞安": "IqWUf",
        "三门": "hsEmE",
        "上虞": "lMqkK",
        "遂昌": "vVqWU",
        "台州": "zWIte",
        "泰顺": "ojdNE",
        "天台": "vhvOJ",
        "桐庐": "psguG",
        "桐乡": "rPEAy",
        "温岭": "IgYwQ",
        "文成": "cGBmo",
        "武义": "qoVEV",
        "仙居": "JhVpH",
        "象山": "GgJvu",
        "萧山": "wdcXE",
        "新昌": "CNewz",
        "义乌": "Izail",
        "永嘉": "ewupG",
        "永康": "VXcDE",
        "余杭": "cMJhE",
        "余姚": "oOdwb",
        "玉环": "DoUMx",
        "云和": "ywpHz",
        "诸暨": "gfWSV",
        "岱山": "uURZs",
        "嵊泗": "hyYAy",
        "衢江": "hhLOl",
        "缙云": "ZESZU"
    },
    "安徽省": {
        "合肥": "xqcji",
        "安庆": "bIpli",
        "蚌埠": "xEdTH",
        "巢湖": "ynBxA",
        "池州": "XbuHL",
        "滁州": "aqZIQ",
        "阜阳": "JcXXt",
        "淮北": "npJUD",
        "淮南": "DUBio",
        "六安": "RLVWB",
        "马鞍山": "cdzPY",
        "宿州": "KZzYj",
        "铜陵": "VAMvd",
        "屯溪": "wnqTm",
        "芜湖": "YCdBx",
        "宣城": "hhgTF",
        "亳州": "bjqNC",
        "长丰": "lUGWB",
        "当涂": "MXyIw",
        "定远": "cSxfG",
        "东至": "ZwTQM",
        "繁昌": "SIWeY",
        "肥东": "JeocZ",
        "肥西": "tdDBE",
        "凤台": "qzDwS",
        "凤阳": "bESbg",
        "阜南": "bHKhs",
        "固镇": "oCQkR",
        "广德": "wyOSJ",
        "含山": "nsdcQ",
        "和县": "vulFs",
        "怀宁": "pomgE",
        "怀远": "HxrdW",
        "黄山": "dFIpc",
        "黄山区": "JsxkK",
        "霍邱": "eqtJL",
        "霍山": "HMeMG",
        "绩溪": "Zvalw",
        "界首": "karbd",
        "金寨": "NjfSe",
        "九华山": "eppay",
        "来安": "DLYqz",
        "郎溪": "sImJG",
        "利辛": "TnLlA",
        "临泉": "wlkiF",
        "灵璧": "GPbvs",
        "庐江": "MmSaS",
        "蒙城": "WfvcH",
        "明光": "eHJSl",
        "南陵": "sWTiK",
        "宁国": "uqTaZ",
        "祁门": "sVPho",
        "潜山": "KivFP",
        "青阳": "tccCZ",
        "全椒": "sYIjP",
        "石台": "QuuWK",
        "寿县": "swcHe",
        "舒城": "VFMGg",
        "宿松": "iScpT",
        "太和": "ddRJw",
        "太湖": "tMAAb",
        "天长": "VHRnN",
        "桐城": "tRaOy",
        "湾沚": "ELCFX",
        "望江": "kABhv",
        "涡阳": "VjERZ",
        "无为": "jOsaC",
        "五河": "wtsbO",
        "萧县": "CKmzv",
        "休宁": "QEyyv",
        "岳西": "GbhPZ",
        "泗县": "CtvRL",
        "泾县": "FqHCb",
        "濉溪": "sCZni",
        "枞阳": "KbOON",
        "歙县": "dkFXw",
        "旌德": "OcJPm",
        "砀山": "Slnbc",
        "颍上": "AUgGn",
        "黟县": "UlADo"
    },
    "福建省": {
        "福州": "djeOy",
        "钓鱼岛": "TPFDQ",
        "建阳": "UXGUr",
        "晋江": "QNUEf",
        "龙岩": "AVWuS",
        "宁德": "uKfig",
        "莆田": "XbBQN",
        "浦城": "lTvde",
        "三明": "CZiRH",
        "厦门": "gDCDS",
        "漳州": "SCyJf",
        "安溪": "hREeH",
        "长乐": "dCAXE",
        "长泰": "BILCs",
        "长汀": "VDGUO",
        "崇武": "qFozG",
        "大田": "vYGga",
        "德化": "MKbSW",
        "东山": "uDfFU",
        "福安": "JNJhg",
        "福鼎": "DmjbL",
        "福清": "OJcaE",
        "古田": "nMfDD",
        "光泽": "mdLfz",
        "华安": "OopEB",
        "建宁": "bFxyH",
        "建瓯": "xQVDJ",
        "将乐": "ebxsQ",
        "连城": "AFZJN",
        "连江": "aOgsa",
        "龙海": "icAJc",
        "罗源": "JZMnV",
        "闽侯": "mvsaF",
        "闽清": "ohLcD",
        "明溪": "WYpkx",
        "南安": "njGuO",
        "南靖": "JTMBG",
        "宁化": "PJKtl",
        "平和": "BFRzc",
        "平潭": "aZFOr",
        "屏南": "hdkzx",
        "清流": "AViZE",
        "泉州": "MGECZ",
        "沙县": "FqHOP",
        "上杭": "mszvd",
        "邵武": "QtQEY",
        "寿宁": "qMckX",
        "顺昌": "znMcP",
        "松溪": "SXdgJ",
        "泰宁": "AAJZf",
        "同安": "lvXIl",
        "武平": "eimDh",
        "武夷山": "zbKCn",
        "霞浦": "ZQgRD",
        "仙游": "iHCBC",
        "秀屿": "vNifC",
        "延平": "cuHtX",
        "永安": "LdOYj",
        "永春": "qBtpj",
        "永定": "XmdVI",
        "永泰": "zgkOw",
        "尤溪": "jPeuC",
        "云霄": "CSeyS",
        "漳平": "LayTz",
        "漳浦": "qVMDu",
        "政和": "lztqa",
        "周宁": "vSWUe",
        "诏安": "EXzXq",
        "柘荣": "GSJpN"
    },
    "江西省": {
        "南昌": "JmxCz",
        "柴桑": "wJyOW",
        "浮梁": "QLKkM",
        "赣县": "eNmid",
        "广昌": "gTbyP",
        "贵溪": "uYodl",
        "吉安县": "ryNCI",
        "景德镇": "DriXU",
        "九江": "kVOgS",
        "临川": "Zvsga",
        "芦溪": "eclSD",
        "庐山": "PCWyN",
        "萍乡": "yBDJf",
        "上栗": "YXrtQ",
        "上饶": "KpYAB",
        "宜春": "OqvoJ",
        "鹰潭": "UWvkt",
        "渝水": "uvdbB",
        "玉山": "eldrT",
        "安福": "AQXam",
        "安义": "OebEp",
        "安远": "zQIQZ",
        "崇仁": "GVeYC",
        "崇义": "OKwKn",
        "大余": "scXAG",
        "德安": "NtswH",
        "德兴": "ObzWw",
        "定南": "VanHB",
        "东乡": "hCKCS",
        "都昌": "lFKRv",
        "分宜": "YjVGY",
        "丰城": "GEceX",
        "奉新": "ElOyt",
        "高安": "ZAypU",
        "共青城": "elBmT",
        "广丰区": "idTyI",
        "广信": "dYuCN",
        "横峰": "JfPmD",
        "湖口": "gFkXT",
        "会昌": "FxLbx",
        "吉水": "xtlYj",
        "金溪": "IxliU",
        "进贤": "CBQqX",
        "井冈山": "cIZPM",
        "靖安": "agoIZ",
        "乐安": "QPXTo",
        "乐平": "LvdkW",
        "黎川": "clOYT",
        "莲花": "aBbtI",
        "龙南": "RwBam",
        "庐山市": "UTmcf",
        "拿山": "pUPQO",
        "南昌县": "Pohqy",
        "南城": "rusOd",
        "南丰": "XcDmx",
        "南康": "xbhYg",
        "宁都": "OXlgc",
        "彭泽": "IWKEq",
        "铅山": "zGnNC",
        "全南": "eXkQd",
        "瑞昌": "qjEqY",
        "瑞金": "OPvLw",
        "三清山": "fzyRB",
        "上高": "TnqCJ",
        "上犹": "OEtxs",
        "石城": "AwiTJ",
        "遂川": "MaPOv",
        "泰和": "BKtiM",
        "铜鼓": "SbQfM",
        "万安": "gVGRT",
        "万年": "Eploe",
        "万载": "SbshZ",
        "武宁": "gEVup",
        "峡江": "pMHJc",
        "新干": "QnqKe",
        "新建": "WQiHO",
        "信丰": "FaYju",
        "兴国": "SNxjz",
        "修水": "kmdsU",
        "寻乌": "dwZOf",
        "宜丰": "lpFTY",
        "宜黄": "RQClf",
        "永丰": "LZRYi",
        "永新": "CsrsV",
        "永修": "XSWiI",
        "于都": "yIXbd",
        "余干": "QIvAP",
        "余江": "vKOSS",
        "樟树": "HWaon",
        "资溪": "rmkXW",
        "鄱阳": "eoKxa",
        "弋阳": "SSTjQ",
        "婺源": "QgJYN"
    },
    "山东省": {
        "济南": "VITKz",
        "滨州": "penbZ",
        "德州": "polCM",
        "东营": "CHtLx",
        "菏泽": "MGAnB",
        "济宁": "Jmcsg",
        "莱芜": "KNtvj",
        "聊城": "XXeBL",
        "临沂": "aGpFP",
        "青岛": "Jrsbf",
        "日照": "GoJQw",
        "泰安": "zUeIF",
        "威海": "KeEOQ",
        "潍坊": "hQrpa",
        "烟台": "qRqdU",
        "枣庄": "rXLkZ",
        "淄博": "BGfNv",
        "安丘": "pBWdT",
        "博山": "cXuJU",
        "博兴": "ssdvr",
        "曹县": "zyMgt",
        "昌乐": "HyQcY",
        "昌邑": "RbeQd",
        "长岛": "OxxPJ",
        "长清": "wpvMw",
        "成山头": "oFjTZ",
        "成武": "fvIrZ",
        "单县": "exVbY",
        "定陶": "lvUtm",
        "东阿": "LGYXk",
        "东明": "bxfmq",
        "东平": "RjKIP",
        "肥城": "totaD",
        "费县": "lIbva",
        "福山": "xRWQS",
        "高密": "UOmID",
        "高青": "rOruH",
        "高唐": "tOfjr",
        "冠县": "bxVRB",
        "广饶": "sbuIu",
        "海阳": "JnxWr",
        "河口": "woPhx",
        "桓台": "dZBBz",
        "黄岛": "KlJLj",
        "惠民": "jiJzG",
        "即墨": "qtBFp",
        "济阳": "pGgRb",
        "嘉祥": "QeBBO",
        "胶州": "QZdFI",
        "金乡": "yMtZS",
        "巨野": "vcePU",
        "垦利": "JdGrX",
        "莱西": "TFySn",
        "莱阳": "qTVLu",
        "莱州": "CxoVZ",
        "兰陵": "ktWtX",
        "乐陵": "HwJwn",
        "利津": "sxcfS",
        "梁山": "XjiXe",
        "临清": "TZrqQ",
        "临邑": "OAUlG",
        "临淄": "EfLlJ",
        "临沭": "JkOIC",
        "临朐": "jUPiO",
        "陵城": "egBEZ",
        "龙口": "hzXej",
        "蒙阴": "FEzHg",
        "牟平": "SvXef",
        "宁津": "jHmKo",
        "宁阳": "XwLyl",
        "蓬莱": "olEzI",
        "平度": "LNoOo",
        "平邑": "WxWXe",
        "平阴": "CGpgS",
        "平原": "aIdOj",
        "栖霞": "OXjTR",
        "齐河": "nejXA",
        "青州": "OxxJw",
        "庆云": "UhSnJ",
        "曲阜": "IzpcI",
        "荣成": "UkLVz",
        "乳山": "yTEhW",
        "商河": "lirNX",
        "石岛": "tQKIy",
        "寿光": "QaFTJ",
        "台儿庄": "BqsRd",
        "微山": "KpFlL",
        "文登": "hfNKh",
        "无棣": "AJubD",
        "武城": "tUgxh",
        "五莲": "xpnot",
        "夏津": "uEdGj",
        "新泰": "iTSlT",
        "薛城": "fDkIG",
        "阳谷": "QlEwu",
        "阳信": "TkSAp",
        "沂南": "zlfuA",
        "沂水": "mxDTK",
        "沂源": "EOZlC",
        "鱼台": "OSlCB",
        "禹城": "TGZZO",
        "沾化": "Aesmb",
        "章丘": "vnSqi",
        "招远": "xwQxT",
        "周村": "yuEhv",
        "诸城": "QOccb",
        "淄川": "kigWn",
        "邹城": "oOSNx",
        "邹平": "CjTiK",
        "兖州": "MCzGo",
        "郓城": "tisSF",
        "郯城": "dWnMY",
        "鄄城": "XjGVI",
        "茌平": "JuJJS",
        "莒南": "Daeda",
        "莒县": "qovBP",
        "莘县": "WsywS",
        "峄城": "Jchqy",
        "崂山": "KtsaK",
        "汶上": "bkOgY",
        "泗水": "hCYEk",
        "滕州": "rTNhe"
    },
    "河南省": {
        "郑州": "YVItN",
        "安阳": "hNkdK",
        "川汇区": "lZXKF",
        "鹤壁": "NYclC",
        "济源": "TJdvk",
        "焦作": "ubXHV",
        "开封": "swtij",
        "南阳": "vRweN",
        "平顶山": "nRecJ",
        "三门峡": "TjcXC",
        "商丘": "aMsMR",
        "新乡": "VLpOH",
        "信阳": "hdKHW",
        "许昌": "ZzMTA",
        "驻马店": "ZmGSj",
        "潢川": "wTUBX",
        "漯河": "lncFZ",
        "濮阳": "XbbBI",
        "宝丰": "nAcuJ",
        "博爱": "DInuO",
        "长葛": "sHlBF",
        "长垣": "tvhjZ",
        "郸城": "uRklp",
        "登封": "QjeZO",
        "邓州": "ALlGb",
        "范县": "pGxSD",
        "方城": "NPIhR",
        "封丘": "OdLdM",
        "扶沟": "Emcgf",
        "巩义": "yrsPS",
        "固始": "liQnS",
        "光山": "sPsZI",
        "滑县": "RMGln",
        "淮滨": "pQUOE",
        "淮阳": "QHPrZ",
        "辉县": "cXwCS",
        "获嘉": "ipyYK",
        "浚县": "mlucC",
        "兰考": "yCGbN",
        "林州": "LvRhA",
        "临颍": "iTyXp",
        "灵宝": "mAGsj",
        "卢氏": "HzXJK",
        "鲁山": "HcTiH",
        "鹿邑": "BNljK",
        "罗山": "rhndw",
        "洛宁": "HaOBO",
        "洛阳": "rYaxY",
        "孟津": "lIgVp",
        "孟州": "aeWfC",
        "泌阳": "ftgII",
        "民权": "UtHHs",
        "南乐": "iJyTs",
        "南召": "XQbzt",
        "内黄": "XHxri",
        "内乡": "RWzAc",
        "宁陵": "lAMXm",
        "平舆": "XdjmX",
        "沁阳": "OAiAk",
        "清丰": "pRxQj",
        "确山": "UCliM",
        "汝南": "vvNHi",
        "汝阳": "onqmI",
        "汝州": "hIncZ",
        "商城": "iDXIG",
        "商水": "PojMH",
        "上蔡": "aBcFs",
        "社旗": "oOUuS",
        "沈丘": "AWlje",
        "遂平": "hsyZH",
        "台前": "gpsQp",
        "太康": "zEzeT",
        "汤阴": "mBYhC",
        "唐河": "jQYDK",
        "通许": "iSvVf",
        "桐柏": "WbHnL",
        "尉氏": "VUIVN",
        "卫辉": "JrcpD",
        "温县": "xfBpE",
        "武陟": "koXUe",
        "舞钢": "tIiAe",
        "舞阳": "aRquF",
        "西华": "GBJUE",
        "西平": "cAtmW",
        "西峡": "rzsUT",
        "息县": "tSCUn",
        "夏邑": "LoNcn",
        "襄城": "MyGEg",
        "项城": "VjWQe",
        "新安": "vMxzb",
        "新蔡": "ORIbm",
        "新密": "LoaLx",
        "新县": "BpKzd",
        "新野": "UcjEf",
        "新郑": "kpoPZ",
        "修武": "zOAjR",
        "延津": "sthkk",
        "叶县": "wJjGK",
        "伊川": "HbtHa",
        "宜阳": "zNQnV",
        "永城": "SMuXc",
        "虞城": "wUEuZ",
        "禹州": "HFqwM",
        "原阳": "ccwBF",
        "镇平": "MqOfh",
        "正阳": "uiooJ",
        "中牟": "KMtvV",
        "偃师": "CwmVv",
        "郏县": "hAfgu",
        "鄢陵": "NbMuX",
        "荥阳": "JAxZP",
        "嵩县": "WKgrt",
        "淇县": "TbHws",
        "淅川": "iamyl",
        "渑池": "XfOYq",
        "杞县": "tCUkl",
        "柘城": "VvHGN",
        "栾川": "mcJvP",
        "睢县": "XMgFC"
    },
    "湖北省": {
        "武汉": "bSpCz",
        "鄂州": "Agzls",
        "恩施": "zKHUp",
        "黄冈": "sWCpi",
        "黄石": "MTZwr",
        "荆门": "vGwSN",
        "荆州": "xBZlA",
        "麻城": "NcQaQ",
        "潜江": "MKtOV",
        "神农架": "liRVu",
        "十堰": "BREJr",
        "随州": "VHSxv",
        "天门": "WxkfH",
        "仙桃": "vAcxm",
        "咸宁": "BokVQ",
        "襄阳": "fTXja",
        "孝感": "CQLZw",
        "宜昌": "ekVpr",
        "宜城": "WAkbT",
        "枣阳": "uGloJ",
        "安陆": "RMZis",
        "巴东": "zJfzY",
        "保康": "oqWyH",
        "蔡甸": "lfZTF",
        "长阳": "uAZAP",
        "赤壁": "KTWwX",
        "崇阳": "fYXOt",
        "大悟": "bmINw",
        "大冶": "LvTkA",
        "丹江口": "ztads",
        "当阳": "LwXQO",
        "房县": "FEijB",
        "公安": "KekHK",
        "谷城": "WjbHS",
        "广水": "Zafip",
        "汉川": "Kogbd",
        "鹤峰": "aTFNA",
        "洪湖": "qYxqF",
        "红安": "OYqFU",
        "黄梅": "YfzjW",
        "黄陂": "Inpll",
        "嘉鱼": "xyZup",
        "监利": "yShDj",
        "建始": "SRuMv",
        "江夏": "XiGox",
        "京山": "zeDBq",
        "来凤": "NNfJp",
        "老河口": "DBJmD",
        "利川": "bLYlG",
        "罗田": "ieWay",
        "南漳": "qCEfB",
        "沙洋": "NSAwY",
        "石首": "NOyuq",
        "松滋": "CHdCL",
        "随县": "zMqDf",
        "通城": "xhjfq",
        "通山": "xNLyS",
        "团风": "pEszq",
        "武穴": "DOsub",
        "五峰": "AAHzJ",
        "咸丰": "KSDOF",
        "孝昌": "QtbbO",
        "新洲": "RZaJI",
        "兴山": "zevgq",
        "宣恩": "FufZg",
        "阳新": "vraeg",
        "夷陵": "hVvAC",
        "夷陵三峡": "bTPcC",
        "宜都": "JHJWL",
        "英山": "aNScZ",
        "应城": "rGLMc",
        "远安": "nRCDs",
        "云梦": "PLBSr",
        "郧西": "dqXoc",
        "郧阳": "MdlIv",
        "枝江": "Bhwex",
        "钟祥": "FLmyq",
        "竹山": "ZVetP",
        "竹溪": "ftxHu",
        "蕲春": "dfWmt",
        "浠水": "HndlP",
        "秭归": "VQNUU"
    },
    "湖南省": {
        "长沙市": "zOenJ",
        "常德": "NMRKc",
        "长沙黄花": "pwvLl",
        "郴州": "cYyyF",
        "赫山": "ljEDf",
        "衡阳": "ObykY",
        "怀化": "pJrqw",
        "吉首": "gWnFP",
        "临武": "MhTjl",
        "娄底": "ZrEsO",
        "南岳": "gMqBs",
        "桑植": "UyXiO",
        "邵阳": "KZYji",
        "望城区": "vcKIn",
        "湘江新区": "htNqQ",
        "湘潭": "tWpqg",
        "永州": "vXgNI",
        "岳阳": "bwVav",
        "张家界": "FOUZo",
        "株洲": "siHjW",
        "沅陵县": "RAzQc",
        "安化": "LTAMD",
        "安仁": "zMNOt",
        "安乡": "ejqKF",
        "保靖": "aDWvQ",
        "茶陵": "cMTxZ",
        "常宁": "zxmLy",
        "辰溪": "PSXSM",
        "城步": "OMJHt",
        "慈利": "QhqHU",
        "道县": "anbCP",
        "东安": "AbmUR",
        "洞口": "AWZQQ",
        "凤凰": "HHWQT",
        "古丈": "gpwLy",
        "桂东": "QaXwQ",
        "桂阳": "OMZne",
        "汉寿": "RvbiI",
        "衡东": "qhQyx",
        "衡南": "GYnJo",
        "衡山": "inRnV",
        "衡阳县": "PMfFu",
        "洪江": "dGOEo",
        "花垣": "aEkzT",
        "华容": "UDpcM",
        "会同": "yzhZl",
        "嘉禾": "CkYws",
        "江华": "dCAYY",
        "江永": "XfpWX",
        "靖州": "WuPCk",
        "蓝山": "RJaJW",
        "冷水江": "gUDwK",
        "冷水滩": "YGosR",
        "涟源": "MvOMQ",
        "临湘": "sabwQ",
        "临澧": "ZskSj",
        "龙山": "czHhG",
        "隆回": "ODQnM",
        "麻阳": "BByTA",
        "南县": "wIetl",
        "宁乡": "vRUXM",
        "宁远": "PKMwh",
        "平江": "PdYcV",
        "祁东": "PHwxt",
        "祁阳": "tjUoi",
        "汝城": "xyZXg",
        "韶山": "ctzSw",
        "邵东": "qChSW",
        "邵阳县": "aFKpi",
        "石门": "ZGIRj",
        "双峰县": "gItui",
        "双牌": "CcRaN",
        "绥宁": "WWGiu",
        "桃江": "rJTxk",
        "桃源": "DYNDO",
        "通道": "uAYSX",
        "武冈": "ZgECL",
        "湘乡": "MFued",
        "湘阴": "EJmro",
        "新化": "FLnON",
        "新晃": "ZOQOg",
        "新宁": "eaueH",
        "新邵": "lMPty",
        "新田": "qxrUF",
        "炎陵": "HDZEq",
        "宜章": "pbfyp",
        "永顺": "LLJXv",
        "永兴": "rwydQ",
        "岳阳县": "shWKT",
        "资兴": "UbStp",
        "攸县": "UUaLX",
        "芷江": "robJO",
        "沅江": "xFxiZ",
        "汨罗": "AlxsQ",
        "泸溪": "XsVCU",
        "浏阳": "eprZJ",
        "溆浦": "ltdEd",
        "澧县": "VdxXV",
        "耒阳": "fzyGq",
        "醴陵": "aSeFW"
    },
    "广东省": {
        "广州": "DwzZf",
        "潮州": "CSTxF",
        "电白": "XEsSv",
        "东莞": "cqsJg",
        "佛冈": "CPZny",
        "高要": "uPyfo",
        "河源": "Fkjlf",
        "鹤山": "TDgRC",
        "惠阳": "VixPE",
        "揭阳": "rUWdQ",
        "萝岗": "IvFqu",
        "茂名": "aELXI",
        "梅县": "dEibM",
        "南海": "MEcHR",
        "南雄": "dzcNI",
        "清远": "WYryQ",
        "饶平": "sgVVw",
        "汕头": "KYhpn",
        "汕尾": "hlwPp",
        "韶关": "fXufo",
        "深圳": "AhpEU",
        "顺德": "cgdeV",
        "阳江": "dCezB",
        "云浮": "JMZwt",
        "湛江": "OKhmr",
        "中山": "YIWau",
        "珠海": "sdnjf",
        "博罗": "dThPV",
        "潮阳": "aDjqK",
        "澄海": "zdeVk",
        "从化": "JNLyH",
        "大埔": "loBTC",
        "德庆": "QZzJe",
        "斗门": "ckONx",
        "恩平": "WdPrA",
        "番禺": "tQOjS",
        "丰顺": "aUKAF",
        "封开": "iZItu",
        "高州": "tHDom",
        "广宁": "ELwZG",
        "海丰": "cPbEV",
        "和平": "kGvmw",
        "花都": "DFILe",
        "化州": "IFnQk",
        "怀集": "EhVeb",
        "惠东": "YMcmt",
        "惠来": "oANdW",
        "蕉岭": "kbdZh",
        "揭西": "iBvsp",
        "开平": "nLwRT",
        "乐昌": "JvNgy",
        "雷州": "pfvjr",
        "连南": "KdUeP",
        "连平": "GawAp",
        "连山": "auxCc",
        "连州": "mvsdx",
        "廉江": "tCFax",
        "龙川": "aalii",
        "龙门": "fNjkZ",
        "陆丰": "BFDXU",
        "罗定": "oUjcx",
        "南澳": "rfGsM",
        "平远": "KidvD",
        "普宁": "XYKTR",
        "仁化": "aDgrE",
        "乳源": "PDmCw",
        "三水": "Akgoq",
        "始兴": "kiynZ",
        "四会": "cTLRb",
        "遂溪": "ZoOgZ",
        "台山": "kRWvm",
        "翁源": "ZzoLx",
        "吴川": "eQFwU",
        "五华": "CSvzA",
        "新丰": "smdvH",
        "新会": "fhvuE",
        "新兴": "guUOJ",
        "信宜": "AtsFe",
        "兴宁": "tOWXk",
        "徐闻": "arOUO",
        "阳春": "bNaey",
        "阳山": "cUuBr",
        "英德": "VOhrT",
        "郁南": "qUoQR",
        "增城": "Cydet",
        "紫金": "CMCDt"
    },
    "广西壮族自治区": {
        "南宁": "dvHfb",
        "百色": "Cejmy",
        "北海": "lBdeM",
        "崇左": "Pnyfc",
        "防城港": "kXkLV",
        "桂林": "qiegc",
        "贵港": "UzLca",
        "河池": "GGGqW",
        "贺州": "SdWDF",
        "来宾": "qxttW",
        "南宁城区": "qGiLL",
        "钦州": "jPyoz",
        "田阳": "DPxlj",
        "梧州": "EUqSO",
        "玉林": "cFeHF",
        "巴马": "lAMQO",
        "北流": "eDcTO",
        "宾阳": "XUOdS",
        "博白": "Glxjb",
        "苍梧": "VyzYZ",
        "大新": "rMrPm",
        "德保": "rBrTd",
        "东兰": "ewvKI",
        "东兴": "yYYyV",
        "都安": "fCFGo",
        "防城": "jOvlz",
        "凤山": "CfJOI",
        "扶绥": "RyKSg",
        "富川": "rCrJo",
        "恭城": "erDXS",
        "灌阳": "odAEb",
        "桂平": "lGcNV",
        "合浦": "hAysq",
        "横州": "KShEg",
        "环江": "ojAnR",
        "金秀": "XuZjF",
        "靖西": "rDUve",
        "乐业": "fvIzP",
        "荔浦": "RJsCy",
        "临桂": "nZlPQ",
        "凌云": "QkgiV",
        "灵川": "QWKYy",
        "灵山": "PrSNs",
        "柳城": "BRgad",
        "柳江": "NdusB",
        "柳州": "hDSje",
        "龙胜": "HYxdu",
        "龙州": "fwsCN",
        "龙圩": "DuQqi",
        "隆安": "GcmlG",
        "隆林": "eIpEZ",
        "鹿寨": "waYqJ",
        "陆川": "Ringx",
        "罗城": "McWVA",
        "马山": "pfTel",
        "蒙山": "FDxZg",
        "那坡": "rDxZb",
        "南丹": "IwXkd",
        "宁明": "VelAS",
        "平果": "EHHiy",
        "平乐": "WwDuG",
        "平南": "TUzGz",
        "凭祥": "EzlaC",
        "浦北": "GKglE",
        "全州": "bEdfI",
        "融安": "zwjGp",
        "融水": "srRpN",
        "容县": "dhbAc",
        "三江": "GHIyC",
        "上林": "BAWNr",
        "上思": "gfZFI",
        "藤县": "cLDZq",
        "天等": "wOjTL",
        "天峨": "pBXxm",
        "田东": "Rtnkn",
        "田林": "NoCNl",
        "武鸣": "MNLCT",
        "武宣": "WUgNU",
        "西林": "lrJzf",
        "象州": "SlPMS",
        "忻城": "Xnwwp",
        "兴安": "ewdcN",
        "阳朔": "rMMFS",
        "宜州": "VxpiW",
        "永福": "SntnR",
        "昭平": "FCRtF",
        "钟山": "zgIKQ",
        "资源": "JWDIo",
        "岑溪": "VnBvF",
        "涠洲岛": "jxnNs",
        "邕宁": "vJqiP"
    },
    "海南省": {
        "海口": "vmEKa",
        "白沙": "AXpuY",
        "保亭": "YoUoQ",
        "澄迈": "tjGqH",
        "定安": "yartD",
        "东方": "wAOgT",
        "黄岩岛": "JereN",
        "乐东": "joRTe",
        "临高": "nqaYV",
        "陵水": "IDWIl",
        "琼海": "tOlIq",
        "琼中": "HgARP",
        "三亚": "PtnWb",
        "屯昌": "VXTVN",
        "万宁": "TtrxS",
        "文昌": "YdxTG",
        "西沙": "vepbp",
        "儋州": "pFFlS",
        "昌江": "vHJCh",
        "南沙": "QUjbu",
        "五指山": "jtadI",
        "中沙": "LwZAm"
    },
    "重庆市": {
        "奉节": "JHIrC",
        "涪陵": "CCvTr",
        "黔江": "iBdYx",
        "巴南": "AbIWr",
        "北碚": "FfkQD",
        "长寿": "mDPjt",
        "城口": "eavwd",
        "大足": "RBIeV",
        "垫江": "OqThL",
        "丰都": "fVOJL",
        "合川": "utLqu",
        "江津": "nIjuT",
        "开州": "DYoqI",
        "梁平": "kWdog",
        "南川": "OIUau",
        "彭水": "mFVrF",
        "荣昌": "klPmX",
        "沙坪坝": "rRKjq",
        "石柱": "bUuhS",
        "铜梁": "uymdU",
        "万盛": "PeJwF",
        "万州": "bsKAn",
        "巫山": "uSMWc",
        "巫溪": "QUGEw",
        "武隆": "LwFjp",
        "秀山": "ukeEi",
        "永川": "XGxHU",
        "酉阳": "bghvn",
        "渝北": "xFVYU",
        "云阳": "pzmmf",
        "忠县": "QHcEb",
        "潼南": "kUNHe",
        "璧山": "ruRPA",
        "綦江": "ivlNL"
    },
    "四川省": {
        "成都": "yGYHR",
        "阿坝": "ujnor",
        "巴中": "UxUlc",
        "达川": "OwVVP",
        "峨眉山": "JKQBL",
        "甘孜": "EvJZp",
        "广安区": "FoeFd",
        "广元": "OwVIj",
        "乐山": "YuAXe",
        "罗江": "aHQGR",
        "眉山": "zkdYW",
        "绵阳": "GcFwG",
        "南充": "vihpz",
        "内江": "wNtyv",
        "攀枝花": "jrDgO",
        "遂宁": "pcHfo",
        "西昌": "Whzpi",
        "雅安": "MfnxC",
        "资阳": "AVVPj",
        "自贡": "MIIAp",
        "泸县": "YIwsD",
        "安岳": "TuuMx",
        "安州": "wCrVC",
        "巴塘": "QYPTJ",
        "白玉": "BSGFT",
        "宝兴": "fbWMU",
        "北川": "Xgqiu",
        "布拖": "rlCwh",
        "苍溪": "QNApE",
        "长宁": "CXrGz",
        "崇州": "VPihc",
        "大邑": "HUYio",
        "大英": "wQKcH",
        "大竹": "mFxpi",
        "丹巴": "TgXGK",
        "丹棱": "TEect",
        "稻城": "Cirzd",
        "道孚": "ISnyf",
        "德昌": "QVWfY",
        "德格": "BLtuX",
        "德阳": "QFQLG",
        "得荣": "gPeiI",
        "都江堰": "GrSbA",
        "峨边": "SlKXy",
        "峨眉": "EuzbB",
        "富顺": "bmhEc",
        "甘洛": "sXvuQ",
        "高县": "ChpSp",
        "古蔺": "JkbCa",
        "广汉": "YXpHm",
        "汉源": "fCUHs",
        "合江": "DprjI",
        "黑水": "laiax",
        "洪雅": "xWemk",
        "红原": "sCzWb",
        "华蓥": "EjrYd",
        "会东": "QcLmg",
        "会理城区": "sEwty",
        "夹江": "XgNyH",
        "简阳": "IhZxf",
        "剑阁": "MfaOt",
        "江安": "EcUZo",
        "江油": "YaiqO",
        "金川": "ngpCL",
        "金堂": "udKik",
        "金阳": "kJJlc",
        "井研": "XkJdi",
        "九龙": "xXGPT",
        "九寨沟": "YZuzT",
        "开江": "Qdtso",
        "康定": "qsqTU",
        "乐至": "YStkV",
        "雷波": "UtzFE",
        "理塘": "AJBNE",
        "理县": "xYIdl",
        "邻水": "EhvQh",
        "龙泉驿": "mqsMW",
        "隆昌": "mKxEY",
        "芦山": "LiKdk",
        "炉霍": "wazHg",
        "马边": "qoufd",
        "马尔康": "FNPwO",
        "茂县": "TgyZk",
        "美姑": "CqHKW",
        "米易": "GQBkM",
        "绵竹": "YxJmk",
        "冕宁": "tGNAv",
        "名山": "FdPbr",
        "木里": "bmyFo",
        "纳溪": "PVPXd",
        "南部": "gGLzn",
        "南江": "viieF",
        "南溪": "VNdMl",
        "宁南": "CGouW",
        "彭山": "sMDUa",
        "彭州": "KKktC",
        "蓬安": "CYTUn",
        "蓬溪": "KxrUp",
        "平昌": "VdEKs",
        "平武": "jWFfG",
        "屏山": "AVDkL",
        "蒲江": "VpUpp",
        "普格": "uERMU",
        "前锋": "cRHwZ",
        "青川": "SzgvK",
        "青神": "eUOGX",
        "渠县": "rTRMZ",
        "壤塘": "zXmXb",
        "仁和": "gmXtJ",
        "仁寿": "PEnFX",
        "荣县": "JizVy",
        "若尔盖": "PwnmG",
        "三台": "pqcSL",
        "色达": "jWXIj",
        "射洪": "eURTs",
        "石棉": "wbIrX",
        "石渠": "ylJwh",
        "什邡": "AKEUu",
        "双流": "grFhZ",
        "松潘": "niBgS",
        "天全": "hcVXJ",
        "通江": "NcACM",
        "万源": "CitjR",
        "旺苍": "yxsyn",
        "威远": "YCPlK",
        "温江": "xrRlZ",
        "武胜": "eqeFJ",
        "五通桥": "TEvfR",
        "西充": "PtFdY",
        "喜德": "eMFmS",
        "乡城": "ccAzh",
        "小金": "ofevQ",
        "新都": "XxQIS",
        "新津": "NZCjp",
        "新龙": "wbJUU",
        "兴文": "ETYKD",
        "叙永": "HGSgX",
        "叙州": "harPc",
        "宣汉": "HVNiO",
        "雅江": "ifYYN",
        "盐边": "BXVJQ",
        "盐亭": "WvCVx",
        "盐源": "eXzMT",
        "仪陇新政": "hvews",
        "宜宾": "wfNOD",
        "营山": "zzseP",
        "越西": "mfrlx",
        "岳池": "yFOsJ",
        "昭觉": "keZZE",
        "中江": "QjPxI",
        "资中": "Ctawc",
        "邛崃": "EVoup",
        "郫都": "NUxad",
        "荥经": "PQOEg",
        "阆中": "rEyHe",
        "沐川": "SHcpz",
        "汶川": "TSnaG",
        "泸定": "wipjP",
        "泸州": "nLWnl",
        "珙县": "ptXbB",
        "梓潼": "ZNNOo",
        "犍为": "LxiRJ",
        "筠连": "mfPnS"
    },
    "贵州省": {
        "贵阳": "SKMHP",
        "毕节": "QJFow",
        "都匀": "EHGgf",
        "凯里": "NSsev",
        "黔西": "xfRzH",
        "水城": "fntCE",
        "铜仁": "EaOOy",
        "兴义": "bUbyg",
        "遵义": "mKDbo",
        "安龙": "fBdei",
        "安顺": "zYxtY",
        "白云": "SOHSv",
        "播州": "ImmpI",
        "册亨": "YkFXJ",
        "长顺": "fuXUe",
        "赤水": "Fyafg",
        "从江": "inRGg",
        "大方": "YDxxS",
        "丹寨": "QfiGH",
        "道真": "efBXm",
        "德江": "WmIeA",
        "独山": "zqguN",
        "凤冈": "FfkVU",
        "福泉": "Bgdxr",
        "关岭": "KqlOa",
        "贵定": "SzwqB",
        "赫章": "CpxKp",
        "花溪": "wWoHD",
        "黄平": "HGQkl",
        "惠水": "OOPMd",
        "剑河": "WXmQk",
        "江口": "vHiWQ",
        "金沙": "foFkP",
        "锦屏": "zFHzB",
        "开阳": "nhvQy",
        "雷山": "XFsWa",
        "黎平": "DrHHS",
        "荔波": "QiOmA",
        "六枝": "XTKOc",
        "龙里": "oSrTE",
        "罗甸": "ddcVF",
        "麻江": "ZERcU",
        "纳雍": "hJPOj",
        "盘州": "QGSkq",
        "平坝": "UYZaj",
        "平塘": "OpPQk",
        "普安": "RYLXT",
        "普定": "xJRLN",
        "清镇": "xCoEZ",
        "晴隆": "rKyfM",
        "仁怀": "avkLt",
        "三都": "WfTTa",
        "三穗": "RMivb",
        "施秉": "REBUD",
        "石阡": "vHFrl",
        "思南": "MyiYN",
        "松桃": "uhZzm",
        "绥阳": "obmwT",
        "台江": "wTTZD",
        "天柱": "bFWLw",
        "桐梓": "WQYWd",
        "万山": "pQUcc",
        "望谟": "hsyBU",
        "威宁": "ZCKHS",
        "瓮安": "DdMaA",
        "乌当": "vDKTW",
        "务川": "hlBSz",
        "息烽": "VBttY",
        "习水": "shhLy",
        "兴仁": "PYXIV",
        "修文": "qYDqu",
        "沿河": "ERvME",
        "印江": "XCIcC",
        "余庆": "gtqrp",
        "玉屏": "ZgWUE",
        "贞丰": "SYwsx",
        "镇宁": "wgmRr",
        "镇远": "FqHqg",
        "正安": "awLJW",
        "织金": "AMmvw",
        "紫云": "aMPck",
        "岑巩": "PjZmd",
        "湄潭": "xUANG",
        "榕江": "tpXDH"
    },
    "云南省": {
        "昆明": "IayMy",
        "保山": "DQgGy",
        "楚雄": "xbekN",
        "大理": "MXvqt",
        "贡山": "EIXjp",
        "红河": "kLDAL",
        "景洪": "mDayj",
        "丽江": "AwEIF",
        "临沧": "oiQQr",
        "芒市": "Wjrex",
        "瑞丽": "dICew",
        "思茅": "qpYuM",
        "文山": "ZQEia",
        "香格里拉": "GtYml",
        "玉溪": "eHman",
        "昭通": "CMqgr",
        "安宁": "bOAGp",
        "宾川": "AQzCk",
        "沧源": "eKeha",
        "昌宁": "oNSGZ",
        "呈贡": "cHXNh",
        "澄江": "mNpXo",
        "大关": "sIkPn",
        "大姚": "adcMw",
        "德钦": "eOoXM",
        "东川": "UgaxN",
        "峨山": "xvRTr",
        "洱源": "jfchA",
        "凤庆": "wpVlw",
        "福贡": "ywnBK",
        "富民": "NYtMq",
        "富宁": "vLEOj",
        "富源": "BrRuR",
        "个旧": "MZnfz",
        "耿马": "ASpgY",
        "广南": "WCNhd",
        "河口": "acADA",
        "鹤庆": "Oepdl",
        "华宁": "cCkAx",
        "华坪": "isoyJ",
        "会泽": "NQkus",
        "剑川": "btlSx",
        "建水": "PzHAZ",
        "江城": "yIZKB",
        "江川": "FvhhF",
        "金平": "bhlMI",
        "晋宁": "lMQXt",
        "景东": "KrpXJ",
        "景谷": "wGNvn",
        "开远": "YdTJG",
        "兰坪": "zOAAs",
        "澜沧": "sMzde",
        "梁河": "zkxjs",
        "六库": "LIOMK",
        "龙陵": "ZVCsS",
        "陇川": "IPydV",
        "鲁甸": "SCUAp",
        "禄丰": "TjOgz",
        "禄劝": "fPIjF",
        "陆良": "eqtuY",
        "绿春": "ebFbI",
        "罗平": "WMKmg",
        "麻栗坡": "KifAk",
        "马关": "jmZgg",
        "马龙": "fyDAe",
        "蒙自": "kXzHY",
        "孟连": "oqzlP",
        "弥渡": "saNmx",
        "弥勒": "tdwdj",
        "墨江": "AOSYX",
        "牟定": "BQsYp",
        "南华": "tJxiW",
        "南涧": "LOAhC",
        "宁洱": "eoMMH",
        "宁蒗": "PtTbw",
        "屏边": "SNyPs",
        "巧家": "vdyEU",
        "丘北": "AFYaW",
        "曲靖": "rYbQI",
        "师宗": "WZsvt",
        "施甸": "qlNLn",
        "石林": "ZrWId",
        "石屏": "aCCnk",
        "双柏": "dqXxh",
        "双江": "MBVyg",
        "绥江": "JiGSi",
        "太华山": "ILlxw",
        "腾冲": "DrwgP",
        "通海": "YOFIz",
        "威信": "msgsX",
        "巍山": "usiSp",
        "维西": "sTINS",
        "武定": "HvkQI",
        "西畴": "KjiDB",
        "西盟": "dDUzR",
        "祥云": "PQqEx",
        "新平": "vVaif",
        "宣威": "kGSGu",
        "寻甸": "OfsjD",
        "盐津": "TJcpS",
        "砚山": "rOuyU",
        "漾濞": "YeTRa",
        "姚安": "mcYHb",
        "宜良": "iXuOK",
        "彝良": "ifitb",
        "易门": "Oqduj",
        "盈江": "NzuxE",
        "永德": "cLAuy",
        "永平": "LwDNZ",
        "永仁": "tUEbc",
        "永善": "PhcCu",
        "永胜": "rJRXL",
        "元江": "noiqK",
        "元谋": "pmumb",
        "元阳": "cXVUi",
        "云龙": "dJvmC",
        "云县": "DIrSp",
        "沾益": "FITcL",
        "镇康": "ZFgiT",
        "镇雄": "YcNIl",
        "镇沅": "XcWKq",
        "勐海": "aqlUk",
        "勐腊": "sGhYv",
        "嵩明": "UYJan",
        "泸西": "cJoUu"
    },
    "西藏自治区": {
        "拉萨": "utJQK",
        "昌都": "FKHOa",
        "林芝": "ulvCs",
        "那曲": "aDeyn",
        "普兰": "gHMZS",
        "日喀则": "wcnpZ",
        "泽当": "BiGFZ",
        "安多": "iVIrH",
        "昂仁": "ASoRj",
        "八宿": "TePqj",
        "巴青": "szXLh",
        "白朗": "uVBXZ",
        "班戈": "enzZH",
        "比如": "sTjgZ",
        "边坝": "LWGKt",
        "波密": "nAOVR",
        "察雅": "hMVZp",
        "察隅": "ATOlN",
        "措美": "JsTgd",
        "措勤": "opQos",
        "错那": "BnUtS",
        "达孜": "IqfNl",
        "当雄": "fXROy",
        "丁青": "pwraz",
        "定结": "UhCTv",
        "定日": "RyXCB",
        "堆龙德庆": "LpaPy",
        "改则": "UYYNe",
        "岗巴": "slNhe",
        "革吉": "RoZcS",
        "工布江达": "nQpHn",
        "贡嘎": "ZBHIZ",
        "贡觉": "MSEXT",
        "吉隆": "MTizD",
        "嘉黎": "wNaRI",
        "加查": "oDAXC",
        "江达": "oaFIV",
        "江孜": "QDuTR",
        "康马": "hojaz",
        "拉孜": "PXSQe",
        "朗县": "OIMSP",
        "浪卡子": "PYgWA",
        "类乌齐": "cnvAw",
        "林周": "LKwJC",
        "隆子": "VrmMl",
        "洛隆": "nIxnv",
        "洛扎": "kloed",
        "芒康": "zLjcY",
        "米林": "eQtyv",
        "墨脱": "eeMPo",
        "墨竹工卡": "aqFzl",
        "南木林": "PTWfQ",
        "尼玛": "mQTEU",
        "尼木": "aypuQ",
        "聂拉木": "Gnhsh",
        "聂荣": "XoVvk",
        "帕里": "ogyxE",
        "琼结": "QIcAs",
        "曲水": "Zdljf",
        "曲松": "dNadf",
        "仁布": "VCtjf",
        "日土": "LEdYG",
        "萨嘎": "cKpCs",
        "萨迦": "cCWKV",
        "桑日": "dUfXr",
        "申扎": "QAkim",
        "狮泉河": "vhADj",
        "双湖": "GmwPa",
        "索县": "cFOMu",
        "谢通门": "xUpde",
        "扎囊": "SbMuy",
        "札达": "lqFFl",
        "仲巴": "SlJsQ",
        "左贡": "zGZrq"
    },
    "陕西省": {
        "西安": "RfjCI",
        "安康": "RprEI",
        "宝鸡": "jrjXm",
        "汉中": "cASRq",
        "秦都": "IVixd",
        "商州": "bwUtG",
        "铜川": "lZvra",
        "延安": "gtpZu",
        "榆林": "eEPbq",
        "安塞": "XKqRX",
        "白河": "eIovq",
        "白水": "lrIpm",
        "彬州": "oodKU",
        "长安": "NnPsM",
        "长武": "RRVoo",
        "陈仓": "XBggT",
        "城固": "aKKWU",
        "澄城": "QobKK",
        "淳化": "jeBQU",
        "大荔": "FvzNQ",
        "丹凤": "HrPSf",
        "定边": "sNYlv",
        "凤县": "KZHTq",
        "凤翔": "vNkSA",
        "佛坪": "nXDqS",
        "扶风": "tcQyi",
        "府谷": "Nudny",
        "富平": "BpoKt",
        "富县": "QfWPS",
        "甘泉": "PWPqX",
        "高陵": "FJzCX",
        "韩城": "cozJM",
        "汉阴": "TwYEu",
        "合阳": "GQDFM",
        "华山": "cKPRS",
        "华阴": "XMEaY",
        "华州": "zVYfc",
        "黄陵": "Iwyeu",
        "黄龙": "uHJpt",
        "佳县": "kNHLa",
        "靖边": "WyIjX",
        "蓝田": "lTwwB",
        "礼泉": "xZaaP",
        "临潼": "zRMYD",
        "留坝": "tejPC",
        "陇县": "fpJEY",
        "略阳": "tKMDB",
        "洛川": "RrumW",
        "洛南": "hmDhb",
        "眉县": "sczdz",
        "米脂": "bLFjW",
        "勉县": "ahPQB",
        "南郑": "FNBBc",
        "宁强": "bjqkU",
        "宁陕": "XbvFE",
        "平利": "yQbHi",
        "蒲城": "tOfoG",
        "千阳": "lQoKf",
        "乾县": "CqlHa",
        "清涧": "prSPO",
        "三原": "ycvtU",
        "山阳": "EGeZr",
        "陕西横山": "nkmKX",
        "商南": "EbthY",
        "神木": "wgIob",
        "石泉": "TlXfd",
        "绥德": "AsHiS",
        "太白": "IztCW",
        "渭南": "fXkRh",
        "吴堡": "GVBLs",
        "吴起": "cdFMC",
        "武功": "dOgXs",
        "西乡": "tWrIf",
        "兴平": "exydQ",
        "旬阳": "uEVEn",
        "旬邑": "HWqri",
        "延长": "zGmNC",
        "延川": "HDzyP",
        "杨凌": "EiWZj",
        "洋县": "lDiMR",
        "耀州": "tfmFL",
        "宜川": "wVXnP",
        "宜君": "rURnf",
        "永寿": "MqOdV",
        "镇安": "tXRiV",
        "镇巴": "RjpPA",
        "镇坪": "AsKPA",
        "志丹": "kTYbH",
        "周至": "YGOXn",
        "紫阳": "qujSt",
        "子长": "zgGer",
        "子洲": "kMChi",
        "柞水": "SifiE",
        "鄠邑": "WJups",
        "岐山": "qmPpg",
        "岚皋": "lpGJm",
        "泾阳": "UuKku",
        "潼关": "ddBPj",
        "麟游": "oxLal"
    },
    "甘肃省": {
        "兰州": "ARkZA",
        "安定": "KrLRa",
        "白银": "soZAZ",
        "嘉峪关": "WVCbx",
        "金昌": "chtaw",
        "酒泉": "vDJSl",
        "临夏": "orIIe",
        "庆城": "eWgYP",
        "天水": "tiBhu",
        "武都": "MyfIx",
        "崆峒": "RfbKS",
        "成县": "fKNTS",
        "崇信": "UGwYi",
        "迭部": "ieEXg",
        "东乡": "XmAHB",
        "敦煌": "iGqZd",
        "甘谷": "dUFbz",
        "皋兰": "RBGMm",
        "高台": "DRGcR",
        "古浪": "NGpEn",
        "瓜州": "aYAhW",
        "广河": "twInP",
        "和政": "jIOPb",
        "合水": "HSTdx",
        "合作": "eLDNl",
        "华池": "IqwuL",
        "华亭": "CUyDL",
        "环县": "tpwqY",
        "徽县": "GGjbv",
        "会宁": "QucKY",
        "金塔": "DpOZG",
        "景泰": "RJphY",
        "静宁": "UFAUV",
        "靖远": "rrWtb",
        "康乐": "ntUYN",
        "康县": "plSyY",
        "礼县": "pEuMT",
        "两当": "XmucV",
        "临潭": "mRFLX",
        "临泽": "xVSVN",
        "临洮": "DtldQ",
        "灵台": "jxyvf",
        "陇西": "IcnHv",
        "碌曲": "sUmbw",
        "玛曲": "CouTD",
        "麦积": "jbIhR",
        "民乐": "rebjh",
        "民勤": "PWOxb",
        "宁县": "lAmjf",
        "秦安": "sSjzn",
        "清水": "RXjrm",
        "山丹": "rpbil",
        "肃北": "sSFnE",
        "肃南": "GGFUG",
        "天祝": "OWolv",
        "通渭": "YKHoa",
        "渭源": "tIClD",
        "文县": "bPRTE",
        "武山": "BjJyr",
        "武威": "LAPGD",
        "西峰": "sXwtL",
        "西和": "sqsLp",
        "夏河": "SDGOR",
        "永昌": "kQQJv",
        "永登": "SRPTQ",
        "永靖": "BjkVk",
        "榆中": "FXosK",
        "玉门": "EydtH",
        "漳县": "oMLOo",
        "张家川": "IZvdZ",
        "张掖": "nvQbo",
        "镇原": "iBsYQ",
        "正宁": "impSE",
        "舟曲": "vfKZw",
        "庄浪": "xClnb",
        "卓尼": "SSAdx",
        "岷县": "KKIqy",
        "泾川": "gtMsI",
        "宕昌": "HoerP"
    },
    "青海省": {
        "西宁": "SHRvr",
        "德令哈": "CEXed",
        "刚察": "atPnu",
        "格尔木": "vBvjN",
        "共和": "IipKM",
        "海晏": "UULnO",
        "河南": "PdgVo",
        "玛沁": "hHWpg",
        "平安": "YUDym",
        "玉树": "MDlNL",
        "班玛": "PTXCN",
        "称多查拉沟": "IIiyA",
        "达日": "zhIdf",
        "大柴旦": "IYNyh",
        "大通": "cNxyI",
        "都兰": "HCwek",
        "甘德": "dyLzr",
        "贵德": "UYGyq",
        "贵南": "ZDODs",
        "互助": "AePoh",
        "化隆": "Mxsvt",
        "尖扎": "rQGTz",
        "久治": "VlYyh",
        "乐都": "TEvmY",
        "玛多": "UbRfU",
        "茫崖": "qbNiS",
        "门源": "oHpvQ",
        "民和": "Wleba",
        "囊谦": "pcEfr",
        "祁连": "QwhuI",
        "曲麻莱": "hbAvz",
        "天峻": "qLNow",
        "同德": "SpzMT",
        "同仁": "bKSuW",
        "乌兰": "SlLAA",
        "兴海": "NYsvc",
        "循化": "nsbuX",
        "杂多": "DQDqH",
        "泽库": "TWXzO",
        "治多": "tlZCx",
        "湟源": "ADbRC",
        "湟中": "eHjuj"
    },
    "宁夏回族自治区": {
        "银川": "LqTRN",
        "固原": "muLnq",
        "石嘴山": "jNMZg",
        "吴忠": "VXPXK",
        "中卫": "mZrCd",
        "海原": "ydxHC",
        "贺兰": "RqsAG",
        "惠农": "eJNvo",
        "灵武": "HYEJD",
        "隆德": "VhNkw",
        "彭阳": "Jiiql",
        "平罗": "yEKbm",
        "青铜峡": "zlWii",
        "陶乐": "wODLX",
        "同心": "OgDeQ",
        "西吉": "zKyVn",
        "盐池": "FsnjH",
        "永宁": "RokyE",
        "中宁": "sEpvS",
        "泾源": "xyYEK"
    },
    "新疆维吾尔自治区": {
        "乌鲁木齐": "lIPam",
        "阿拉尔": "uWWmy",
        "阿勒泰": "SnOYy",
        "阿图什": "SzKmL",
        "博乐": "hSwcs",
        "哈密": "LFhJu",
        "和田": "HDzeq",
        "克拉玛依": "RHxwy",
        "奇台": "AWxpU",
        "沙湾": "NcLcb",
        "石河子": "JGBUK",
        "塔城": "qHPXG",
        "吐鲁番": "DGEdf",
        "伊宁": "Zfpil",
        "阿合奇": "yPnAd",
        "阿克苏": "wPpQt",
        "阿克陶": "LEeJY",
        "阿拉山口": "LrfAz",
        "阿瓦提": "EvmKC",
        "巴楚": "maCEn",
        "巴里坤": "ELQMW",
        "巴仑台": "Tbgnv",
        "巴音布鲁克": "BNxlq",
        "拜城": "jcFzJ",
        "博湖": "GPrnI",
        "布尔津": "OCkda",
        "蔡家湖": "WRyLq",
        "策勒": "LqeGf",
        "察布查尔": "qqWkF",
        "昌吉": "bIfiH",
        "达坂城": "wmimk",
        "额敏": "BFpxB",
        "福海": "dzMlI",
        "阜康": "FoOEx",
        "富蕴": "JUKYd",
        "巩留": "FsktL",
        "哈巴河": "vuVKP",
        "和布克赛尔": "UXCKY",
        "和静": "ZsUMo",
        "和硕": "XpzXk",
        "呼图壁": "RYXfs",
        "霍城": "cuwlP",
        "霍尔果斯": "QEpMD",
        "吉木乃": "Evjap",
        "吉木萨尔": "IaCfC",
        "精河": "bpMAs",
        "喀什": "aHjQA",
        "柯坪": "SkZBu",
        "库车": "BVaDD",
        "库尔勒": "qQedw",
        "轮台": "QMLyD",
        "洛浦": "HQoif",
        "玛纳斯": "YQXUS",
        "麦盖提": "BCzpJ",
        "米东区": "gIolY",
        "民丰": "zxIeh",
        "莫索湾": "YslWW",
        "墨玉": "nbFjx",
        "木垒": "HvGJL",
        "尼勒克": "eGeWh",
        "炮台": "CZSbw",
        "皮山": "WupeJ",
        "且末": "vsSYw",
        "青河": "KUgXP",
        "若羌": "ropjq",
        "莎车": "fhaom",
        "沙雅": "lHafw",
        "塔什库尔干": "jhHpN",
        "塔中": "tlkso",
        "特克斯": "piUzn",
        "天池": "WiYil",
        "铁干里克": "jaCzk",
        "托克逊": "xKqfo",
        "托里": "eseSA",
        "尉犁": "RpLvF",
        "温泉": "QGHxV",
        "温宿": "oVenj",
        "乌鲁木齐牧试站": "OQSHg",
        "乌恰": "fNxHG",
        "乌什": "CUUUw",
        "乌苏": "VDvKy",
        "小渠子": "GSWoG",
        "新和": "QGLHi",
        "新源": "hrqYY",
        "焉耆": "QiKzF",
        "叶城": "baeXx",
        "伊宁县": "ZuktQ",
        "伊吾": "fvHql",
        "英吉沙": "zXMMB",
        "于田": "eKceY",
        "裕民": "EDyyx",
        "岳普湖": "zEUul",
        "泽普": "aFKNj",
        "昭苏": "SQKGX",
        "伽师": "lTSgf",
        "鄯善": "zVdtO"
    },
    "香港特别行政区": {
        "香港天文台": "hcBhy"
    },
    "澳门特别行政区": {
        "大潭山": "RQqyQ"
    },
    "台湾省": {
        "台北": "VrMVF",
        "高雄": "Urwjw",
        "台中": "FYDSf"
    }
}